astypes/__init__.py
astypes/_ass.py
astypes/_ast.py
astypes/_handlers.py
astypes/_helpers.py
astypes/_type.py
astypes/py.typed
astypes-0.2.6.dist-info/LICENSE
astypes-0.2.6.dist-info/WHEEL
astypes-0.2.6.dist-info/METADATA
astypes-0.2.6.dist-info/RECORD
