Metadata-Version: 2.1
Name: astypes
Version: 0.2.6
Summary: Infer types for AST nodes.
Keywords: typing,annotations,type annotations,ast,astroid
Author-email: Gram <git@orsinium.dev>
Requires-Python: >=3.8
Classifier: Development Status :: 5 - Production/Stable
Classifier: Intended Audience :: Developers
Classifier: License :: OSI Approved :: MIT License
Classifier: Programming Language :: Python
Classifier: Typing :: Typed
Requires-Dist: astroid
Requires-Dist: typeshed_client
Requires-Dist: flake8 ; extra == "lint"
Requires-Dist: isort ; extra == "lint"
Requires-Dist: mypy ; extra == "lint"
Requires-Dist: types-protobuf ; extra == "lint"
Requires-Dist: unify ; extra == "lint"
Requires-Dist: pytest ; extra == "test"
Requires-Dist: pytest-cov ; extra == "test"
Project-URL: Source, https://github.com/orsinium-labs/astypes
Provides-Extra: lint
Provides-Extra: test
